pypsn/__init__.py
pypsn-0.2.3.dist-info/LICENSE
pypsn-0.2.3.dist-info/METADATA
pypsn-0.2.3.dist-info/WHEEL
pypsn-0.2.3.dist-info/top_level.txt
pypsn-0.2.3.dist-info/RECORD
