Metadata-Version: 2.1
Name: pypsn
Version: 0.2.3
Summary: PosiStageNet parser
Author-email: vanous <noreply@nodomain.com>
Maintainer-email: vanous <noreply@nodomain.com>
License: MIT License
Project-URL: Repository, https://github.com/open-stage/python-psn
Project-URL: Changelog, https://github.com/open-stage/python-psn/blob/master/CHANGELOG.md
Keywords: PSN,PosiStageNet
Classifier: Development Status :: 4 - Beta
Classifier: Programming Language :: Python
Requires-Python: >=3.8
License-File: LICENSE
